odoo/addons/stock_release_channel_show_volume/README.rst
odoo/addons/stock_release_channel_show_volume/__init__.py
odoo/addons/stock_release_channel_show_volume/__manifest__.py
odoo/addons/stock_release_channel_show_volume/data/decimal_precision.xml
odoo/addons/stock_release_channel_show_volume/i18n/it.po
odoo/addons/stock_release_channel_show_volume/i18n/stock_release_channel_show_volume.pot
odoo/addons/stock_release_channel_show_volume/models/__init__.py
odoo/addons/stock_release_channel_show_volume/models/stock_release_channel.py
odoo/addons/stock_release_channel_show_volume/readme/CONTRIBUTORS.rst
odoo/addons/stock_release_channel_show_volume/readme/DESCRIPTION.rst
odoo/addons/stock_release_channel_show_volume/static/description/icon.png
odoo/addons/stock_release_channel_show_volume/static/description/index.html
odoo/addons/stock_release_channel_show_volume/tests/__init__.py
odoo/addons/stock_release_channel_show_volume/tests/test_channel_computed_fields.py
odoo/addons/stock_release_channel_show_volume/views/release_channel.xml
odoo_addon_stock_release_channel_show_volume-16.0.1.1.0.2.dist-info/METADATA
odoo_addon_stock_release_channel_show_volume-16.0.1.1.0.2.dist-info/WHEEL
odoo_addon_stock_release_channel_show_volume-16.0.1.1.0.2.dist-info/top_level.txt
odoo_addon_stock_release_channel_show_volume-16.0.1.1.0.2.dist-info/RECORD
